zun_ui/__init__.py
zun_ui/karma.conf.js
zun_ui/models.py
zun_ui/version.py
zun_ui/api/__init__.py
zun_ui/api/client.py
zun_ui/api/rest_api.py
zun_ui/content/__init__.py
zun_ui/content/cloud_shell/__init__.py
zun_ui/content/cloud_shell/views.py
zun_ui/content/container/__init__.py
zun_ui/content/container/capsules/__init__.py
zun_ui/content/container/capsules/panel.py
zun_ui/content/container/capsules/urls.py
zun_ui/content/container/containers/__init__.py
zun_ui/content/container/containers/admin_urls.py
zun_ui/content/container/containers/panel.py
zun_ui/content/container/containers/tests.py
zun_ui/content/container/containers/urls.py
zun_ui/content/container/containers/views.py
zun_ui/content/container/hosts/__init__.py
zun_ui/content/container/hosts/panel.py
zun_ui/content/container/hosts/urls.py
zun_ui/content/container/images/__init__.py
zun_ui/content/container/images/panel.py
zun_ui/content/container/images/urls.py
zun_ui/enabled/_0330_cloud_shell.py
zun_ui/enabled/_1330_project_container_panelgroup.py
zun_ui/enabled/_1331_project_container_containers_panel.py
zun_ui/enabled/_1332_project_container_capsules_panel.py
zun_ui/enabled/_2330_admin_container_panelgroup.py
zun_ui/enabled/_2331_admin_container_images_panel.py
zun_ui/enabled/_2332_admin_container_hosts_panel.py
zun_ui/enabled/_2333_admin_container_containers_panel.py
zun_ui/enabled/__init__.py
zun_ui/locale/de/LC_MESSAGES/django.po
zun_ui/locale/de/LC_MESSAGES/djangojs.po
zun_ui/locale/en_GB/LC_MESSAGES/django.po
zun_ui/locale/en_GB/LC_MESSAGES/djangojs.po
zun_ui/locale/id/LC_MESSAGES/django.po
zun_ui/locale/id/LC_MESSAGES/djangojs.po
zun_ui/locale/ja/LC_MESSAGES/django.po
zun_ui/locale/ja/LC_MESSAGES/djangojs.po
zun_ui/locale/ko_KR/LC_MESSAGES/django.po
zun_ui/locale/ko_KR/LC_MESSAGES/djangojs.po
zun_ui/locale/ru/LC_MESSAGES/django.po
zun_ui/locale/ru/LC_MESSAGES/djangojs.po
zun_ui/locale/tr_TR/LC_MESSAGES/django.po
zun_ui/locale/zh_Hans/LC_MESSAGES/django.po
zun_ui-16.0.0.dist-info/AUTHORS
zun_ui-16.0.0.dist-info/LICENSE
zun_ui-16.0.0.dist-info/METADATA
zun_ui-16.0.0.dist-info/WHEEL
zun_ui-16.0.0.dist-info/pbr.json
zun_ui-16.0.0.dist-info/top_level.txt
zun_ui-16.0.0.dist-info/RECORD
